Metadata-Version: 1.0
Name: ankitar26681845
Version: 1.0
Summary: Calculate and visuallize, Gaussian, Binomial and Normal distributions
Home-page: UNKNOWN
Author: UNKNOWN
Author-email: ankitbhardvaj18@gmail.com
License: UNKNOWN
Platform: UNKNOWN
